{
"lowlevel": {
    "average_loudness": 0.908984720707,
    "barkbands_crest": {
        "dmean": 4.06613492966,
        "dmean2": 6.68937206268,
        "dvar": 12.6562948227,
        "dvar2": 32.4446678162,
        "max": 26.5348758698,
        "mean": 15.9689826965,
        "median": 14.9090499878,
        "min": 3.71239733696,
        "var": 30.1193408966
    },
    "barkbands_flatness_db": {
        "dmean": 0.0382832847536,
        "dmean2": 0.0595604516566,
        "dvar": 0.00130456232,
        "dvar2": 0.00295829540119,
        "max": 0.439331382513,
        "mean": 0.250868827105,
        "median": 0.251838207245,
        "min": 0.0407955534756,
        "var": 0.00723202060908
    },
    "barkbands_kurtosis": {
        "dmean": 31.926366806,
        "dmean2": 52.0185127258,
        "dvar": 3909.21826172,
        "dvar2": 7389.23583984,
        "max": 717.728149414,
        "mean": 57.8483772278,
        "median": 30.7344551086,
        "min": -1.41616976261,
        "var": 8986.70800781
    },
    "barkbands_skewness": {
        "dmean": 1.78334856033,
        "dmean2": 2.93391394615,
        "dvar": 4.17793321609,
        "dvar2": 10.2885913849,
        "max": 20.0598297119,
        "mean": 4.13410139084,
        "median": 3.45359563828,
        "min": 0.446426093578,
        "var": 8.9684677124
    },
    "barkbands_spread": {
        "dmean": 6.51903152466,
        "dmean2": 10.2157335281,
        "dvar": 173.654541016,
        "dvar2": 470.611480713,
        "max": 102.302871704,
        "mean": 12.5314941406,
        "median": 4.24145460129,
        "min": 0.272689431906,
        "var": 416.641662598
    },
    "dissonance": {
        "dmean": 0.0412328056991,
        "dmean2": 0.065787576139,
        "dvar": 0.00111235212535,
        "dvar2": 0.00250195059925,
        "max": 0.498574823141,
        "mean": 0.36029446125,
        "median": 0.366886168718,
        "min": 0.159565359354,
        "var": 0.00710397912189
    },
    "dynamic_complexity": 9.00347137451,
    "erbbands_crest": {
        "dmean": 3.9109749794,
        "dmean2": 6.3143286705,
        "dvar": 13.837846756,
        "dvar2": 28.4646587372,
        "max": 28.4837474823,
        "mean": 17.331861496,
        "median": 18.3742599487,
        "min": 2.96290707588,
        "var": 43.4166526794
    },
    "erbbands_flatness_db": {
        "dmean": 0.032313529402,
        "dmean2": 0.0462980307639,
        "dvar": 0.000888129288796,
        "dvar2": 0.00154839153402,
        "max": 0.402937203646,
        "mean": 0.220336034894,
        "median": 0.234141260386,
        "min": 0.024829056114,
        "var": 0.00887843407691
    },
    "erbbands_kurtosis": {
        "dmean": 10.1207065582,
        "dmean2": 14.4336500168,
        "dvar": 170.304138184,
        "dvar2": 263.942993164,
        "max": 194.352279663,
        "mean": 21.5284519196,
        "median": 11.3723831177,
        "min": -1.06309354305,
        "var": 1027.68383789
    },
    "erbbands_skewness": {
        "dmean": 0.88545280695,
        "dmean2": 1.31370306015,
        "dvar": 0.8065995574,
        "dvar2": 1.47233343124,
        "max": 10.5407972336,
        "mean": 2.94648218155,
        "median": 2.74719381332,
        "min": -0.249833762646,
        "var": 3.62590646744
    },
    "erbbands_spread": {
        "dmean": 6.28108453751,
        "dmean2": 9.45190048218,
        "dvar": 71.9803390503,
        "dvar2": 156.109222412,
        "max": 90.4287643433,
        "mean": 17.5686893463,
        "median": 9.34957695007,
        "min": 0.724715590477,
        "var": 420.680877686
    },
    "hfc": {
        "dmean": 2.16305470467,
        "dmean2": 3.03810405731,
        "dvar": 33.299041748,
        "dvar2": 52.4266738892,
        "max": 72.6471862793,
        "mean": 3.93650770187,
        "median": 1.44871914387,
        "min": 0.216576963663,
        "var": 70.691619873
    },
    "melbands_crest": {
        "dmean": 4.49546289444,
        "dmean2": 7.47516775131,
        "dvar": 21.5522289276,
        "dvar2": 49.2278823853,
        "max": 36.569026947,
        "mean": 19.8960056305,
        "median": 19.0223922729,
        "min": 7.48341751099,
        "var": 36.82081604
    },
    "melbands_flatness_db": {
        "dmean": 0.0380119755864,
        "dmean2": 0.0571643561125,
        "dvar": 0.00138903525658,
        "dvar2": 0.00314355012961,
        "max": 0.557325065136,
        "mean": 0.361380070448,
        "median": 0.368322759867,
        "min": 0.0947044417262,
        "var": 0.00990450195968
    },
    "melbands_kurtosis": {
        "dmean": 16.074760437,
        "dmean2": 25.4178600311,
        "dvar": 344.28729248,
        "dvar2": 817.571166992,
        "max": 148.417602539,
        "mean": 29.528585434,
        "median": 22.3963756561,
        "min": 0.656142234802,
        "var": 700.814941406
    },
    "melbands_skewness": {
        "dmean": 1.03375816345,
        "dmean2": 1.64795589447,
        "dvar": 1.04206430912,
        "dvar2": 2.68486762047,
        "max": 9.03163909912,
        "mean": 2.55850791931,
        "median": 2.32610559464,
        "min": -0.77996635437,
        "var": 2.78807783127
    },
    "melbands_spread": {
        "dmean": 2.59798288345,
        "dmean2": 4.27976560593,
        "dvar": 32.0181312561,
        "dvar2": 95.5914001465,
        "max": 48.9606971741,
        "mean": 4.72858095169,
        "median": 2.61823034286,
        "min": 0.402701258659,
        "var": 35.8593330383
    },
    "pitch_salience": {
        "dmean": 0.11641395092,
        "dmean2": 0.18628063798,
        "dvar": 0.0119220465422,
        "dvar2": 0.0290990360081,
        "max": 0.815547645092,
        "mean": 0.494694560766,
        "median": 0.513494133949,
        "min": 0.112842202187,
        "var": 0.0289506819099
    },
    "silence_rate_20dB": {
        "dmean": 0,
        "dmean2": 0,
        "dvar": 0,
        "dvar2": 0,
        "max": 1,
        "mean": 1,
        "median": 1,
        "min": 1,
        "var": 0
    },
    "silence_rate_30dB": {
        "dmean": 0.0105820102617,
        "dmean2": 0.021276595071,
        "dvar": 0.0104700215161,
        "dvar2": 0.0208239164203,
        "max": 1,
        "mean": 0.984210550785,
        "median": 1,
        "min": 0,
        "var": 0.0155401844531
    },
    "silence_rate_60dB": {
        "dmean": 0.121693119407,
        "dmean2": 0.244680851698,
        "dvar": 0.106883794069,
        "dvar2": 0.227364987135,
        "max": 1,
        "mean": 0.415789484978,
        "median": 0,
        "min": 0,
        "var": 0.242908701301
    },
    "spectral_centroid": {
        "dmean": 102.259475708,
        "dmean2": 163.600753784,
        "dvar": 52713.34375,
        "dvar2": 139044.15625,
        "max": 2329.3190918,
        "mean": 469.778015137,
        "median": 330.303527832,
        "min": 205.172653198,
        "var": 137279.109375
    },
    "spectral_complexity": {
        "dmean": 0.751322746277,
        "dmean2": 1.21808505058,
        "dvar": 1.08630812168,
        "dvar2": 2.04286432266,
        "max": 10,
        "mean": 2.85263156891,
        "median": 3,
        "min": 0,
        "var": 4.1677646637
    },
    "spectral_decrease": {
        "dmean": 1.78474413026e-09,
        "dmean2": 2.47209541726e-09,
        "dvar": 2.09866441665e-17,
        "dvar2": 3.29314167619e-17,
        "max": -3.08612597283e-12,
        "mean": -3.12383696688e-09,
        "median": -1.02183783657e-09,
        "min": -5.89444475452e-08,
        "var": 4.80611755141e-17
    },
    "spectral_energy": {
        "dmean": 0.0069302697666,
        "dmean2": 0.0096020642668,
        "dvar": 0.000317304278724,
        "dvar2": 0.000497973000165,
        "max": 0.22905883193,
        "mean": 0.0121471146122,
        "median": 0.00398712372407,
        "min": 3.65682353731e-05,
        "var": 0.000725023273844
    },
    "spectral_energyband_high": {
        "dmean": 1.89402783235e-06,
        "dmean2": 3.34248056788e-06,
        "dvar": 4.50413664699e-11,
        "dvar2": 1.33603447749e-10,
        "max": 7.27631704649e-05,
        "mean": 9.19393914955e-06,
        "median": 8.48685522215e-06,
        "min": 4.78897436551e-06,
        "var": 2.50948879732e-11
    },
    "spectral_energyband_low": {
        "dmean": 0.000340159371262,
        "dmean2": 0.00040283985436,
        "dvar": 4.08307698763e-07,
        "dvar2": 3.3827367929e-07,
        "max": 0.00876741670072,
        "mean": 0.00100385723636,
        "median": 0.000250369252171,
        "min": 4.83663279738e-06,
        "var": 3.30947250404e-06
    },
    "spectral_energyband_middle_high": {
        "dmean": 5.73507604713e-05,
        "dmean2": 6.98017029208e-05,
        "dvar": 1.75425896032e-08,
        "dvar2": 2.52586094263e-08,
        "max": 0.00151401304174,
        "mean": 9.60986872087e-05,
        "median": 3.10996401822e-05,
        "min": 8.91017236881e-07,
        "var": 4.5316042474e-08
    },
    "spectral_energyband_middle_low": {
        "dmean": 0.00680061569437,
        "dmean2": 0.00941398646683,
        "dvar": 0.000314280419843,
        "dvar2": 0.000494323729072,
        "max": 0.228169083595,
        "mean": 0.0117077762261,
        "median": 0.00365868443623,
        "min": 2.58855152424e-06,
        "var": 0.000715961272363
    },
    "spectral_entropy": {
        "dmean": 0.341916114092,
        "dmean2": 0.505777657032,
        "dvar": 0.116310782731,
        "dvar2": 0.214976251125,
        "max": 8.43180084229,
        "mean": 6.20898628235,
        "median": 6.0715379715,
        "min": 4.12261533737,
        "var": 1.17743599415
    },
    "spectral_flux": {
        "dmean": 0.0248139780015,
        "dmean2": 0.0427656285465,
        "dvar": 0.00137194071431,
        "dvar2": 0.00454521551728,
        "max": 0.269050717354,
        "mean": 0.0393169485033,
        "median": 0.0274917557836,
        "min": 0.00418931711465,
        "var": 0.0015200052876
    },
    "spectral_kurtosis": {
        "dmean": 5.16736888885,
        "dmean2": 6.99441289902,
        "dvar": 35.5741615295,
        "dvar2": 67.5775604248,
        "max": 90.2338943481,
        "mean": 22.431936264,
        "median": 18.4787044525,
        "min": 3.10403203964,
        "var": 241.979476929
    },
    "spectral_rms": {
        "dmean": 0.000763897551224,
        "dmean2": 0.00102375575807,
        "dvar": 1.15145996915e-06,
        "dvar2": 1.63966694799e-06,
        "max": 0.0149489808828,
        "mean": 0.00251119676977,
        "median": 0.00197227671742,
        "min": 0.00018888177874,
        "var": 5.54473808734e-06
    },
    "spectral_rolloff": {
        "dmean": 1248.24182129,
        "dmean2": 2426.9519043,
        "dvar": 16478750,
        "dvar2": 47058760,
        "max": 20112.0117188,
        "mean": 1223.76647949,
        "median": 344.53125,
        "min": 21.533203125,
        "var": 13059890
    },
    "spectral_skewness": {
        "dmean": 0.435867637396,
        "dmean2": 0.594817459583,
        "dvar": 0.175823256373,
        "dvar2": 0.360223531723,
        "max": 7.97849750519,
        "mean": 3.74829125404,
        "median": 3.5370182991,
        "min": 1.46507239342,
        "var": 1.65104997158
    },
    "spectral_spread": {
        "dmean": 846983.6875,
        "dmean2": 1096976.875,
        "dvar": 1.32579380429e+12,
        "dvar2": 1.77042738381e+12,
        "max": 18169650,
        "mean": 4782069,
        "median": 3878171.5,
        "min": 1327142.625,
        "var": 7.5076337664e+12
    },
    "spectral_strongpeak": {
        "dmean": 0.323133736849,
        "dmean2": 0.47674036026,
        "dvar": 0.213450968266,
        "dvar2": 0.346911907196,
        "max": 4.14057731628,
        "mean": 0.692708969116,
        "median": 0.425174742937,
        "min": 0,
        "var": 0.670722544193
    },
    "zerocrossingrate": {
        "dmean": 0.0196552574635,
        "dmean2": 0.0256243757904,
        "dvar": 0.00100704748183,
        "dvar2": 0.00188567873556,
        "max": 0.31884765625,
        "mean": 0.0635690763593,
        "median": 0.0322265625,
        "min": 0.0048828125,
        "var": 0.00490885274485
    },
    "barkbands": {
        "dmean": [0.0001660373091, 6.06144840276e-06, 6.09485396126e-05, 0.000623267726041, 0.000897763180546, 0.00588764296845, 0.000171273350134, 0.000126013997942, 6.08118862147e-05, 3.98084048356e-05, 1.4781912796e-05, 9.58718919719e-06, 9.54961706157e-06, 4.77419234812e-06, 5.9071535361e-06, 2.05421588362e-06, 1.37083134177e-06, 7.07940330358e-07, 8.22517620236e-07, 5.27028248598e-07, 3.0373195159e-07, 2.26266536174e-07, 1.61591273695e-07, 2.66227544898e-07, 2.65280817757e-07, 2.20071811441e-07, 9.07273260964e-07],
        "dmean2": [0.000304456014419, 1.07350369944e-05, 7.58118258091e-05, 0.00077108934056, 0.0012829513289, 0.00873852521181, 0.000285812682705, 0.000148690349306, 8.81568121258e-05, 5.80867090321e-05, 1.81766081369e-05, 1.478003378e-05, 1.44772302519e-05, 7.73699048295e-06, 9.45352167037e-06, 3.20594381265e-06, 2.00238218895e-06, 1.19165906654e-06, 1.32733657665e-06, 8.64665139488e-07, 5.32388412466e-07, 4.15604517912e-07, 2.90008301818e-07, 4.88529678933e-07, 4.86838757752e-07, 4.00147996515e-07, 1.56728674483e-06],
        "dvar": [6.67020572109e-08, 2.46603432119e-10, 1.62816728988e-08, 1.94325207303e-06, 4.23286064688e-06, 0.000301929627312, 2.69364903716e-07, 3.52509573531e-07, 1.53789958546e-08, 1.75750631826e-08, 1.59221480445e-09, 1.02898711773e-09, 7.36040783877e-10, 1.15391397826e-10, 2.84790635519e-10, 1.10856983315e-11, 5.52399619103e-12, 1.45910388806e-12, 2.20087359795e-12, 1.50861983496e-12, 1.60227961541e-12, 1.72354047267e-12, 3.28109420059e-13, 1.170838166e-12, 9.46493968271e-13, 3.40433817204e-13, 7.36677320708e-13],
        "dvar2": [1.97416852643e-07, 7.37785721405e-10, 2.17759001941e-08, 2.56006751442e-06, 8.7349972091e-06, 0.000492530642077, 5.13639974997e-07, 4.53733008499e-07, 2.38367210414e-08, 3.1834101577e-08, 1.95009342008e-09, 2.4934643239e-09, 1.39978184599e-09, 3.16686454838e-10, 8.55743642614e-10, 2.58898891908e-11, 9.66563114269e-12, 3.89650768248e-12, 4.80954642432e-12, 4.06200767467e-12, 4.72560532372e-12, 5.12068686065e-12, 9.557110962e-13, 3.46208868865e-12, 2.79090400963e-12, 9.98762921325e-13, 1.46622004902e-12],
        "max": [0.00164231960662, 0.000167391466675, 0.00176009105053, 0.0219442024827, 0.0212955046445, 0.208621308208, 0.00349987507798, 0.00743984710425, 0.0016656286316, 0.00139408546966, 0.000436636386439, 0.000390987232095, 0.00030429547769, 9.39383608056e-05, 0.000162387485034, 3.19350656355e-05, 2.99875573546e-05, 7.37609479984e-06, 1.74868728209e-05, 1.02221056295e-05, 1.25764454424e-05, 1.31245787998e-05, 5.18144042871e-06, 1.04877744889e-05, 9.08831862034e-06, 5.51817811356e-06, 9.65558047028e-06],
        "mean": [0.000172779036802, 7.97006759967e-06, 0.000160411960678, 0.00165929086506, 0.0010405498324, 0.00852352008224, 0.000205694959732, 0.000162574273418, 8.1343925558e-05, 5.31432815478e-05, 2.18179575313e-05, 1.146474915e-05, 1.1653058209e-05, 5.94150424149e-06, 6.83881125951e-06, 2.80859444501e-06, 1.92929496734e-06, 1.04091964204e-06, 1.24560870063e-06, 7.62478407523e-07, 4.34438277352e-07, 2.8004862429e-07, 2.75467073152e-07, 4.34134989291e-07, 5.14439818744e-07, 6.75843409681e-07, 7.36579841032e-06],
        "median": [4.96185784868e-05, 4.12737335864e-06, 1.0277302863e-05, 0.00035494347685, 0.000321011757478, 0.00193191680592, 2.64181853709e-05, 1.58897382789e-05, 2.47564130404e-05, 5.67733377466e-06, 3.85450039175e-06, 3.16526120514e-06, 2.67398036158e-06, 2.63124388766e-06, 2.14600277104e-06, 1.37781125886e-06, 8.76340664036e-07, 4.76385253023e-07, 6.35276023786e-07, 3.88207126889e-07, 2.41102156906e-07, 1.54659090867e-07, 1.8037272298e-07, 2.85267191202e-07, 3.45391157452e-07, 6.19524598733e-07, 7.34832974558e-06],
        "min": [1.65310268585e-07, 1.03404460106e-07, 8.80353709931e-08, 1.94242929297e-07, 6.72798705637e-07, 3.57281692231e-07, 1.9896089043e-07, 4.15614103133e-08, 1.123806328e-07, 8.59055688807e-08, 3.78173119486e-08, 6.45516706754e-08, 5.00818586602e-08, 3.91921233245e-08, 7.92389158732e-08, 3.58890339669e-08, 4.08385325557e-08, 4.43908199088e-08, 4.15351273375e-08, 4.11604972328e-08, 4.59818174647e-08, 6.22847267095e-08, 7.36334584417e-08, 1.43251355667e-07, 1.91736731381e-07, 3.6781383983e-07, 8.97917061593e-07],
        "var": [9.12182755997e-08, 2.02827268869e-10, 1.2044860398e-07, 1.27129205794e-05, 6.04601882515e-06, 0.000551795470528, 3.85977784845e-07, 5.38334290923e-07, 3.37093233327e-08, 2.99414786298e-08, 4.22784074416e-09, 1.04711961324e-09, 9.11056452502e-10, 1.0188541677e-10, 3.03253366862e-10, 1.5550285018e-11, 1.11588342733e-11, 1.95939705433e-12, 3.65708765354e-12, 1.43015113641e-12, 9.23953513525e-13, 9.14142459646e-13, 1.93941068175e-13, 6.50464599718e-13, 5.34934943563e-13, 1.97580206319e-13, 8.94026931479e-13]
    },
    "erbbands": {
        "dmean": [0.000702376419213, 0.00107584567741, 0.0494791045785, 1.01839852333, 1.59548723698, 2.32501292229, 38.8974876404, 35.2723731995, 3.60756611824, 2.97648882866, 1.56835258007, 1.38487946987, 1.49166786671, 0.908919632435, 0.454611122608, 0.483388155699, 0.474499166012, 0.253535330296, 0.318101376295, 0.181549757719, 0.120093978941, 0.0825464501977, 0.0386038124561, 0.0329482331872, 0.0430300273001, 0.024317862466, 0.0169582087547, 0.00847428012639, 0.0060824630782, 0.00873639713973, 0.00468092039227, 0.00652297725901, 0.00389693211764, 0.00363604351878, 0.0016365617048, 0.000909483002033, 0.000390251603676, 0.000242386420723, 0.000121384895465, 2.58045511146e-05],
        "dmean2": [0.00125641433988, 0.00140253687277, 0.0555856637657, 1.20903503895, 2.15933561325, 3.34346342087, 58.9685516357, 49.1965713501, 5.39848470688, 4.17297840118, 1.90737867355, 2.05263853073, 2.28842186928, 1.25043833256, 0.564923465252, 0.734852671623, 0.699513316154, 0.393430560827, 0.491602420807, 0.293683946133, 0.183223068714, 0.119515694678, 0.0646355524659, 0.0521759949625, 0.0712250322104, 0.039769295603, 0.0293742772192, 0.0148196779191, 0.0108761182055, 0.0165069755167, 0.0085559329018, 0.0122807305306, 0.00692786835134, 0.00677107041702, 0.00290449662134, 0.00164347141981, 0.000700639677234, 0.000415815797169, 0.000198664623895, 4.1733848775e-05],
        "dvar": [2.49762774729e-06, 2.99967359751e-06, 0.008216236718, 5.00928974152, 12.3018932343, 22.2974739075, 10626.9023438, 11759.5175781, 85.8209533691, 80.114440918, 43.1024551392, 8.02619075775, 20.5632610321, 7.98245954514, 1.5638679266, 2.85110425949, 2.10243034363, 0.361748218536, 0.43115618825, 0.314750701189, 0.0421708524227, 0.025164861232, 0.00476823374629, 0.00341757806018, 0.00646602921188, 0.00317967659794, 0.00472610862926, 0.00114836764988, 0.000712458975613, 0.00313472235575, 0.000240762892645, 0.00126437225845, 9.9720331491e-05, 0.00025246743462, 1.98955403903e-05, 9.54635106609e-06, 9.96747530735e-07, 4.28843165423e-08, 1.1881300388e-08, 5.60276380845e-10],
        "dvar2": [7.39574943509e-06, 5.5735240494e-06, 0.00823015999049, 4.97202730179, 24.5294036865, 45.260509491, 17895.6367188, 18245.3964844, 145.438369751, 108.779266357, 70.1583709717, 12.7009086609, 36.9713287354, 16.6080646515, 2.300563097, 6.86373233795, 3.81963396072, 0.977480649948, 1.162514925, 0.851682960987, 0.101461745799, 0.0460661835968, 0.0130790742114, 0.00720731820911, 0.0143344672397, 0.00844289548695, 0.0139466496184, 0.00339144584723, 0.00208714720793, 0.00931861624122, 0.000703606056049, 0.00377056119032, 0.000279589236015, 0.000752403691877, 5.58884858037e-05, 2.75504644378e-05, 2.91003379971e-06, 1.16836304187e-07, 3.10003045456e-08, 1.1130877331e-09],
        "max": [0.017016960308, 0.017131773755, 1.14915144444, 33.192199707, 52.7194900513, 43.0118942261, 1023.00268555, 1466.13916016, 61.9348182678, 101.160339355, 82.3701553345, 35.2459793091, 42.5854568481, 33.8619613647, 19.5637149811, 20.9349079132, 16.7039794922, 5.33347082138, 6.33197164536, 6.70443582535, 1.67133569717, 2.09842181206, 0.423077076674, 0.741603910923, 0.766377806664, 0.473629891872, 0.680694282055, 0.340784698725, 0.263258159161, 0.557208776474, 0.134431794286, 0.353183180094, 0.0779577493668, 0.152984037995, 0.0344512462616, 0.0266059134156, 0.00927191320807, 0.00220181979239, 0.00135590403806, 0.000398274889449],
        "mean": [0.00108322943561, 0.00277994642965, 0.147051781416, 3.03200387955, 3.28461122513, 3.01674246788, 55.3846969604, 52.8282432556, 5.02390098572, 3.97489023209, 2.16164731979, 1.8305182457, 2.08852481842, 1.08448898792, 0.720121026039, 0.561415374279, 0.592251479626, 0.331350237131, 0.381765812635, 0.233376994729, 0.16155025363, 0.113773845136, 0.0605013482273, 0.0536730401218, 0.063704662025, 0.0377258434892, 0.023452905938, 0.0128231225535, 0.00902683567256, 0.00987836532295, 0.00794177036732, 0.00880081392825, 0.00732435099781, 0.00634038215503, 0.00330605218187, 0.00173385301605, 0.00129095523153, 0.00135503674392, 0.0008156846161, 0.000158581562573],
        "median": [0.000551876204554, 0.00100376526825, 0.0236226078123, 0.605694651604, 0.760831475258, 0.856128931046, 9.40612030029, 9.48718261719, 0.921052455902, 0.810260295868, 0.37825345993, 0.562133789062, 0.32073572278, 0.18149471283, 0.184199780226, 0.150490894914, 0.134235650301, 0.130542188883, 0.139965549111, 0.092110350728, 0.0784895867109, 0.0518895722926, 0.0280105397105, 0.0268356800079, 0.0312927737832, 0.0197365339845, 0.0119477845728, 0.0077688023448, 0.00557916611433, 0.00526031758636, 0.00511097116396, 0.0053721293807, 0.00529786944389, 0.00408281711861, 0.00240766489878, 0.00125325948466, 0.00119654636364, 0.00133192003705, 0.000804957933724, 0.000153990491526],
        "min": [2.1057723643e-05, 4.65201737825e-05, 0.00023652992968, 0.000592561962549, 0.000626285502221, 0.00267504388466, 0.00423760944977, 0.00328114000149, 0.00396293634549, 0.00456766411662, 0.00343314628117, 0.00287961703725, 0.00299994670786, 0.00273698219098, 0.00205204449594, 0.00198545283638, 0.00228439480998, 0.00321763171814, 0.00353271863423, 0.00265336944722, 0.00273569743149, 0.00266339094378, 0.00265606679022, 0.00233402312733, 0.0024528496433, 0.00184144685045, 0.00215416774154, 0.00211136718281, 0.00226823380217, 0.00233067478985, 0.00221669627354, 0.00259067770094, 0.00252444460057, 0.00216160737909, 0.0012683524983, 0.000804825802334, 0.000697475799825, 0.000461803429062, 0.000132654589834, 1.40407246363e-05],
        "var": [2.73819068752e-06, 1.53760993271e-05, 0.0718335583806, 37.8730354309, 50.2811584473, 34.5885696411, 17902.6386719, 24492.3457031, 142.700744629, 132.729125977, 59.561466217, 16.9562606812, 36.7644233704, 12.7351036072, 4.08864402771, 2.95712924004, 2.63107275963, 0.332214295864, 0.53930336237, 0.31581902504, 0.0539648793638, 0.0434381552041, 0.00611241674051, 0.00719590811059, 0.0093133719638, 0.00325337960385, 0.00276906904764, 0.000671268848237, 0.000405333965318, 0.00163203687407, 0.000143747995025, 0.000661793921608, 7.12873079465e-05, 0.000135035574203, 1.36247390401e-05, 5.56990653422e-06, 6.0087802467e-07, 5.20863530085e-08, 1.50256287412e-08, 1.23333943058e-09]
    },
    "gfcc": {
        "mean": [-189.819168091, 96.7383728027, -47.0046730042, -21.9183006287, -43.5209999084, -30.811750412, -45.2234077454, -21.5804462433, -23.0887413025, -8.78735637665, -7.18153715134, -5.08245229721, -2.36201500893],
        "cov": [[3530.16040039, 2059.0456543, -675.777709961, -515.637390137, -332.657440186, -391.721466064, -368.671661377, -248.08605957, -378.206634521, -209.901351929, -157.922698975, -261.5574646, -96.7891998291], [2059.0456543, 1627.75317383, -97.1766891479, -407.038482666, -272.751251221, -341.271057129, -279.246704102, -250.445907593, -281.132720947, -196.916671753, -127.162055969, -171.698532104, -101.527786255], [-675.777709961, -97.1766891479, 534.220336914, 135.993026733, -45.4058227539, -34.3821907043, -47.1786651611, -54.5459709167, 17.0460262299, -12.1433792114, 5.90479564667, 33.754650116, -26.2956867218], [-515.637390137, -407.038482666, 135.993026733, 257.149505615, 95.382019043, 43.8406639099, 24.4875679016, 39.7284469604, 58.5035743713, 51.4430122375, 33.0028381348, 30.3770599365, 7.88572788239], [-332.657440186, -272.751251221, -45.4058227539, 95.382019043, 152.013946533, 98.9653701782, 81.4341506958, 42.0995635986, 39.607875824, 31.129989624, 23.8774852753, 28.1749992371, 24.4317150116], [-391.721466064, -341.271057129, -34.3821907043, 43.8406639099, 98.9653701782, 188.046417236, 125.922721863, 71.4465789795, 51.6744880676, 26.887638092, 22.8366317749, 48.8970832825, 32.9954032898], [-368.671661377, -279.246704102, -47.1786651611, 24.4875679016, 81.4341506958, 125.922721863, 146.42578125, 88.5139389038, 58.0921707153, 17.1866493225, 5.80818414688, 27.4371204376, 15.0702362061], [-248.08605957, -250.445907593, -54.5459709167, 39.7284469604, 42.0995635986, 71.4465789795, 88.5139389038, 107.175888062, 75.4256515503, 29.0941963196, 1.98392760754, 6.52110385895, 2.18486666679], [-378.206634521, -281.132720947, 17.0460262299, 58.5035743713, 39.607875824, 51.6744880676, 58.0921707153, 75.4256515503, 99.9197845459, 56.2490348816, 14.963145256, 11.0748538971, -7.21522426605], [-209.901351929, -196.916671753, -12.1433792114, 51.4430122375, 31.129989624, 26.887638092, 17.1866493225, 29.0941963196, 56.2490348816, 72.745513916, 40.4041366577, 16.0256290436, 5.12800216675], [-157.922698975, -127.162055969, 5.90479564667, 33.0028381348, 23.8774852753, 22.8366317749, 5.80818414688, 1.98392760754, 14.963145256, 40.4041366577, 58.2412261963, 41.9238586426, 21.4390621185], [-261.5574646, -171.698532104, 33.754650116, 30.3770599365, 28.1749992371, 48.8970832825, 27.4371204376, 6.52110385895, 11.0748538971, 16.0256290436, 41.9238586426, 78.6224594116, 51.9423980713], [-96.7891998291, -101.527786255, -26.2956867218, 7.88572788239, 24.4317150116, 32.9954032898, 15.0702362061, 2.18486666679, -7.21522426605, 5.12800216675, 21.4390621185, 51.9423980713, 80.4348983765]],
        "icov": [[0.0131788449362, -0.0178242437541, 0.0170694179833, -0.0147958090529, 0.013485044241, -0.0130025390536, 0.0133466189727, -0.00926204677671, 0.00877324026078, -0.00622468674555, 0.00319570372812, 0.00207525654696, -0.00162843451835], [-0.0178242437541, 0.0278767663985, -0.0233602728695, 0.0239544119686, -0.0190886035562, 0.0198881775141, -0.0161393471062, 0.0126298936084, -0.00647774059325, 0.00965115241706, -0.0037507279776, -0.000356648757588, 0.00410749018192], [0.0170694179833, -0.0233602728695, 0.026478016749, -0.0232943296432, 0.0213909279555, -0.0174274276942, 0.015327216126, -0.0045026470907, 0.00377509417012, -0.00230427482165, 0.00314235594124, 0.000286688300548, -0.000641217455268], [-0.0147958090529, 0.0239544119686, -0.0232943296432, 0.0306062828749, -0.0243940297514, 0.0178250018507, -0.00745021179318, 0.00116458639968, 0.00125490245409, 0.00128801574465, -0.000847290735692, -0.00156411947682, 0.00454412493855], [0.013485044241, -0.0190886035562, 0.0213909279555, -0.0243940297514, 0.0327076762915, -0.0179909747094, 0.00387051771395, 0.00254540028982, 4.98265944771e-05, -0.00115803710651, -0.00187569682021, 0.00589471729472, -0.00506016658619], [-0.0130025390536, 0.0198881775141, -0.0174274276942, 0.0178250018507, -0.0179909747094, 0.0297234151512, -0.0221177730709, 0.00804125703871, -0.00337379262783, 0.00390687398612, -0.00132106128149, -0.00554311927408, 0.00258969026618], [0.0133466189727, -0.0161393471062, 0.015327216126, -0.00745021179318, 0.00387051771395, -0.0221177730709, 0.0450124330819, -0.0295588225126, 0.0153863243759, -0.00559961190447, 0.00801549479365, -0.00277609564364, 0.00309001468122], [-0.00926204677671, 0.0126298936084, -0.0045026470907, 0.00116458639968, 0.00254540028982, 0.00804125703871, -0.0295588225126, 0.0563196279109, -0.0429503209889, 0.0238034538925, -0.0101666366681, 0.00746622448787, -0.004334946163], [0.00877324026078, -0.00647774059325, 0.00377509417012, 0.00125490245409, 4.98265944771e-05, -0.00337379262783, 0.0153863243759, -0.0429503209889, 0.0741990432143, -0.0489124208689, 0.0272159967571, -0.0096426429227, 0.011891442351], [-0.00622468674555, 0.00965115241706, -0.00230427482165, 0.00128801574465, -0.00115803710651, 0.00390687398612, -0.00559961190447, 0.0238034538925, -0.0489124208689, 0.0712262392044, -0.0468329116702, 0.0206908751279, -0.00684342253953], [0.00319570372812, -0.0037507279776, 0.00314235594124, -0.000847290735692, -0.00187569682021, -0.00132106128149, 0.00801549479365, -0.0101666366681, 0.0272159967571, -0.0468329116702, 0.0657716467977, -0.0357107706368, 0.0110648563132], [0.00207525654696, -0.000356648757588, 0.000286688300548, -0.00156411947682, 0.00589471729472, -0.00554311927408, -0.00277609564364, 0.00746622448787, -0.0096426429227, 0.0206908751279, -0.0357107706368, 0.0528502203524, -0.0237000323832], [-0.00162843451835, 0.00410749018192, -0.000641217455268, 0.00454412493855, -0.00506016658619, 0.00258969026618, 0.00309001468122, -0.004334946163, 0.011891442351, -0.00684342253953, 0.0110648563132, -0.0237000323832, 0.0288743842393]]
    },
    "melbands": {
        "dmean": [9.76798401098e-06, 1.40456950248e-05, 0.00021142695914, 7.32976477593e-05, 0.00109245558269, 0.000882217427716, 3.56417040166e-05, 3.38416721206e-05, 1.17156614579e-05, 8.77169713931e-06, 7.26872440282e-06, 3.60695480595e-06, 1.72089517037e-06, 1.12029067623e-06, 9.02027466054e-07, 9.81098878583e-07, 4.46270831844e-07, 4.86817157253e-07, 4.76497689306e-07, 1.08340316274e-07, 1.47836502151e-07, 9.36224893167e-08, 4.25157296036e-08, 3.11825445465e-08, 2.56623700068e-08, 3.8174462702e-08, 2.26103775702e-08, 1.57118016375e-08, 1.21423413546e-08, 7.55372564498e-09, 4.07227984667e-09, 2.82382006667e-09, 5.8857341223e-09, 4.33216040818e-09, 2.69949063103e-09, 2.77232592438e-09, 4.54691573282e-09, 2.48906539824e-09, 2.93214807989e-09, 3.41020456318e-09],
        "dmean2": [1.75605982804e-05, 1.75284712896e-05, 0.00026229568175, 0.00010954971367, 0.00163043336943, 0.00126265676226, 5.66839626117e-05, 4.58592112409e-05, 1.37789202199e-05, 1.32253362608e-05, 1.13770711323e-05, 5.12362521476e-06, 2.04161551665e-06, 1.68901954112e-06, 1.31308297568e-06, 1.50242442487e-06, 7.26065593426e-07, 7.55056703383e-07, 7.92159880803e-07, 1.62498679401e-07, 2.28595439467e-07, 1.38268191563e-07, 7.28240650005e-08, 5.18716376519e-08, 3.98257853362e-08, 6.22433660169e-08, 3.79168980658e-08, 2.60896761972e-08, 2.1433834263e-08, 1.34786013462e-08, 7.15886727676e-09, 4.89989249175e-09, 1.11351576848e-08, 8.1171176447e-09, 4.96326224564e-09, 4.99831420697e-09, 8.61887272663e-09, 4.35598845883e-09, 5.2205479939e-09, 6.53750698021e-09],
        "dvar": [3.18324311355e-10, 8.63034477216e-10, 2.13924778336e-07, 1.61834687873e-08, 8.11469635664e-06, 7.28337727196e-06, 1.30795410058e-08, 1.41368463602e-08, 1.89110926918e-09, 2.57173338181e-10, 4.98283525552e-10, 1.20312329543e-10, 1.95657240409e-11, 1.4329685008e-11, 5.58358524347e-12, 7.91116044202e-12, 1.25573976131e-12, 9.50846714733e-13, 2.59051460838e-12, 3.34779912939e-14, 6.72515767576e-14, 3.22780166582e-14, 6.44238860122e-15, 2.64257381236e-15, 2.14356743313e-15, 5.1076048603e-15, 2.15335743994e-15, 1.63783550643e-15, 2.38863185247e-15, 1.12328691965e-15, 1.85648803556e-16, 6.71209884705e-17, 1.60810888514e-15, 5.819649449e-16, 6.55090649195e-17, 8.96520648674e-17, 6.9799442969e-16, 2.58407302525e-17, 6.88317700308e-17, 2.52246385223e-16],
        "dvar2": [9.25638898863e-10, 1.14377285421e-09, 2.90373066036e-07, 3.59897818214e-08, 1.35449781737e-05, 1.14964022941e-05, 2.34033645796e-08, 1.79526367106e-08, 2.98052671432e-09, 4.47509335144e-10, 9.13284781134e-10, 2.67717237268e-10, 2.57308636203e-11, 3.24406855545e-11, 1.01137605235e-11, 1.6160371652e-11, 3.51753738984e-12, 2.36778630557e-12, 7.60864808658e-12, 7.57669141728e-14, 1.67995717164e-13, 5.36586461299e-14, 1.7621449818e-14, 6.77030173664e-15, 4.47262152919e-15, 1.10516674615e-14, 5.19592202109e-15, 4.52721110857e-15, 7.04368797311e-15, 3.31206928914e-15, 5.4551579369e-16, 1.85490567214e-16, 4.79380583488e-15, 1.72224710418e-15, 1.88770159672e-16, 2.63710949694e-16, 2.08296667268e-15, 7.09124138215e-17, 1.94964114568e-16, 7.5074229475e-16],
        "max": [0.000176423345692, 0.000395761075197, 0.00736525561661, 0.00169803854078, 0.0292447526008, 0.0351118147373, 0.000844449386932, 0.00142298347782, 0.000533458951395, 0.000190296705114, 0.000201961986022, 0.000126614322653, 6.52029557386e-05, 4.96370703331e-05, 2.61816858256e-05, 3.06863330479e-05, 1.01401801658e-05, 8.38098549139e-06, 1.80168171937e-05, 2.06467689168e-06, 1.89588297417e-06, 2.34339722738e-06, 5.02655268519e-07, 3.21137264336e-07, 6.08913978795e-07, 7.7414460975e-07, 4.25251016622e-07, 3.6843084672e-07, 4.8374505468e-07, 3.32169321382e-07, 1.3731511217e-07, 7.18344494999e-08, 4.00223711949e-07, 2.38936081587e-07, 6.24696951945e-08, 9.11697384254e-08, 2.62919030547e-07, 4.57223237049e-08, 7.28976843334e-08, 1.51105339796e-07],
        "mean": [1.39325748023e-05, 3.69143781427e-05, 0.000572201795876, 0.000123982565128, 0.00155449530575, 0.0013021195773, 4.58085632999e-05, 4.36185255239e-05, 1.60565523402e-05, 1.13005435196e-05, 9.97016923066e-06, 4.0249678932e-06, 2.62721073341e-06, 1.46095112541e-06, 1.19944979815e-06, 1.16644980608e-06, 5.396793199e-07, 5.79372226639e-07, 5.19295610957e-07, 1.78441908361e-07, 1.87017576536e-07, 1.27535230376e-07, 6.09493966408e-08, 4.79763997419e-08, 4.07258191615e-08, 5.35294937265e-08, 3.29937144272e-08, 2.3650077452e-08, 1.58034385578e-08, 9.98411398001e-09, 6.53289555785e-09, 4.70072647474e-09, 5.99432237181e-09, 5.07655029125e-09, 4.42079972629e-09, 4.71999994645e-09, 5.56128165741e-09, 4.83003725904e-09, 5.355044852e-09, 5.38865663202e-09],
        "median": [5.63620596949e-06, 3.31192086378e-06, 0.000138288945891, 4.85085838591e-05, 0.000304248649627, 0.000258286047028, 6.56915153741e-06, 7.73265219323e-06, 2.63508536591e-06, 3.59786281479e-06, 1.42439762385e-06, 6.18014951215e-07, 5.77504465582e-07, 4.25958205597e-07, 2.92983600048e-07, 3.1007493817e-07, 2.20202750256e-07, 2.2457938087e-07, 1.59396392974e-07, 9.89081456737e-08, 9.27098753323e-08, 5.38190398913e-08, 2.52024499048e-08, 2.41783446597e-08, 1.93968325846e-08, 2.76590697013e-08, 1.54086627902e-08, 1.24280195024e-08, 7.66981411715e-09, 5.33755617482e-09, 4.02261512988e-09, 3.08033376584e-09, 2.95282776008e-09, 2.88442270069e-09, 2.83217449493e-09, 3.073639121e-09, 3.27912985654e-09, 3.59172580566e-09, 3.5693905609e-09, 3.42652928254e-09],
        "min": [1.64909636169e-07, 4.47310455343e-08, 1.14907429349e-07, 1.22737603192e-07, 1.41335860349e-07, 6.44024069629e-08, 5.59151338564e-08, 3.12038359596e-08, 2.67982436242e-08, 1.56740700419e-08, 1.48200571815e-08, 9.56792600704e-09, 5.4357616186e-09, 7.06170499853e-09, 4.8641455308e-09, 2.89942958531e-09, 4.35808100718e-09, 4.42136061096e-09, 3.88812226859e-09, 3.42361849981e-09, 3.19168913521e-09, 2.59778931699e-09, 2.08649231226e-09, 1.95158222915e-09, 1.35453170902e-09, 1.64579783135e-09, 1.12684173104e-09, 1.1116078058e-09, 1.18663667781e-09, 1.09350095645e-09, 1.197449917e-09, 1.20029119977e-09, 9.68295665871e-10, 1.17374843178e-09, 1.09188158515e-09, 1.26266364031e-09, 1.40514189173e-09, 1.44876011188e-09, 1.55719859229e-09, 1.72237879514e-09],
        "var": [4.84167317349e-10, 6.25428819845e-09, 1.38811901707e-06, 4.89132290227e-08, 1.39435069286e-05, 1.44354298754e-05, 1.99783745103e-08, 2.25486456173e-08, 2.86482038092e-09, 5.26799104339e-10, 8.61304971789e-10, 1.75485903586e-10, 5.46879971863e-11, 1.72092253642e-11, 8.84724064842e-12, 8.46182585806e-12, 1.02377481492e-12, 1.14654206268e-12, 2.38724209671e-12, 5.89362746431e-14, 7.92876167824e-14, 5.85664058483e-14, 8.36156366585e-15, 3.73361535238e-15, 4.78565483682e-15, 7.40876002041e-15, 2.64015870967e-15, 1.45630152275e-15, 1.39552045016e-15, 6.19866916432e-16, 1.19397764245e-16, 4.7807588408e-17, 8.34511259195e-16, 3.07073980865e-16, 4.11237539917e-17, 5.29899047242e-17, 3.62270962283e-16, 2.15004292061e-17, 4.5978629208e-17, 1.3337319907e-16]
    },
    "mfcc": {
        "mean": [-871.917175293, 169.161331177, 32.1656646729, 13.163939476, 8.50260639191, -11.1399030685, -11.1575956345, -19.4073295593, -15.342622757, -9.69647216797, -13.0352964401, -9.7889251709, -5.03420305252],
        "cov": [[3870.78662109, 1764.54333496, -645.469360352, -311.558685303, -324.562591553, -376.456665039, -156.76399231, -344.25177002, -291.052978516, -173.232513428, -306.661071777, -296.175018311, -229.01272583], [1764.54333496, 1388.43371582, -41.4002380371, -198.508102417, -213.128051758, -241.978240967, -143.107803345, -222.597320557, -214.528900146, -190.089126587, -235.516342163, -199.697662354, -128.275665283], [-645.469360352, -41.4002380371, 460.611633301, 108.075500488, 38.076965332, 4.66156959534, -64.5406341553, -15.576259613, -40.89037323, -60.8147735596, -8.21883964539, 1.21214330196, -4.77806282043], [-311.558685303, -198.508102417, 108.075500488, 186.302078247, 80.6152420044, 14.2867002487, -16.2720546722, -19.5455760956, -9.81091594696, 3.58751511574, 14.9646806717, 9.07495594025, 6.54104089737], [-324.562591553, -213.128051758, 38.076965332, 80.6152420044, 105.092781067, 70.0534515381, 28.2610092163, 18.6116466522, 15.9184169769, 23.4564628601, 19.5292472839, 22.0209941864, 31.6298046112], [-376.456665039, -241.978240967, 4.66156959534, 14.2867002487, 70.0534515381, 127.730209351, 78.0262298584, 63.6194458008, 45.9362487793, 30.9760971069, 34.518447876, 42.1083869934, 42.5851593018], [-156.76399231, -143.107803345, -64.5406341553, -16.2720546722, 28.2610092163, 78.0262298584, 103.596992493, 75.2290496826, 47.4012107849, 31.3115024567, 18.1857719421, 24.6485233307, 29.3828277588], [-344.25177002, -222.597320557, -15.576259613, -19.5455760956, 18.6116466522, 63.6194458008, 75.2290496826, 128.637023926, 87.6523666382, 37.4009895325, 44.4499740601, 45.2941513062, 31.5235233307], [-291.052978516, -214.528900146, -40.89037323, -9.81091594696, 15.9184169769, 45.9362487793, 47.4012107849, 87.6523666382, 111.484657288, 64.1963272095, 50.1083526611, 41.3680076599, 19.8862915039], [-173.232513428, -190.089126587, -60.8147735596, 3.58751511574, 23.4564628601, 30.9760971069, 31.3115024567, 37.4009895325, 64.1963272095, 87.6837997437, 61.3108215332, 35.7664375305, 16.810005188], [-306.661071777, -235.516342163, -8.21883964539, 14.9646806717, 19.5292472839, 34.518447876, 18.1857719421, 44.4499740601, 50.1083526611, 61.3108215332, 89.0600585938, 65.8541488647, 29.7171459198], [-296.175018311, -199.697662354, 1.21214330196, 9.07495594025, 22.0209941864, 42.1083869934, 24.6485233307, 45.2941513062, 41.3680076599, 35.7664375305, 65.8541488647, 85.6438217163, 53.5804824829], [-229.01272583, -128.275665283, -4.77806282043, 6.54104089737, 31.6298046112, 42.5851593018, 29.3828277588, 31.5235233307, 19.8862915039, 16.810005188, 29.7171459198, 53.5804824829, 65.7322998047]],
        "icov": [[0.00160757242702, -0.00140963785816, 0.00228786491789, -0.000330529583152, 0.000318858394166, 0.000460144656245, 0.000146983191371, 3.21439183608e-05, 0.0019247692544, -0.00106097979005, 0.00169215211645, -0.00159456033725, 0.00274025090039], [-0.00140963785816, 0.00400870433077, -0.00221171532758, 0.00244288798422, 0.00119686347898, 0.00158989813644, -0.000905951310415, 0.0021082686726, -0.000812620390207, 0.00157986301929, 0.00221109832637, 0.0017813667655, -0.00231404229999], [0.00228786491789, -0.00221171532758, 0.00676953978837, -0.00249532214366, 0.000676789029967, -0.00186953961384, 0.00448196474463, -0.0026773691643, 0.00379259418696, 0.000611628696788, 0.0019297208637, -0.00258888956159, 0.00449534785002], [-0.000330529583152, 0.00244288798422, -0.00249532214366, 0.0133105386049, -0.0112709393725, 0.00756613584235, -0.00383453024551, 0.00553010078147, -0.00202084518969, 0.00424165232107, -0.00206652842462, -3.91081921407e-05, 0.00218622013927], [0.000318858394166, 0.00119686347898, 0.000676789029967, -0.0112709393725, 0.0327901504934, -0.0169944893569, 0.00688826851547, -0.00237574311905, 0.00561390584335, -0.0108361830935, 0.00938816089183, 0.00441553862765, -0.00886153429747], [0.000460144656245, 0.00158989813644, -0.00186953961384, 0.00756613584235, -0.0169944893569, 0.0310007371008, -0.0199351012707, 0.00697383377701, -0.00510776881129, 0.00848229136318, -0.00524017866701, -0.00175369891804, 0.000651831331197], [0.000146983191371, -0.000905951310415, 0.00448196474463, -0.00383453024551, 0.00688826851547, -0.0199351012707, 0.0369218029082, -0.0207629464567, 0.0104456562549, -0.013483710587, 0.0129565084353, -0.000686178333126, -0.00250505725853], [3.21439183608e-05, 0.0021082686726, -0.0026773691643, 0.00553010078147, -0.00237574311905, 0.00697383377701, -0.0207629464567, 0.0355367809534, -0.0237243343145, 0.0175631288439, -0.0117014469579, 0.00359933800064, -0.00261272280477], [0.0019247692544, -0.000812620390207, 0.00379259418696, -0.00202084518969, 0.00561390584335, -0.00510776881129, 0.0104456562549, -0.0237243343145, 0.0391931347549, -0.0261919125915, 0.0167443696409, -0.0111271934584, 0.00925393775105], [-0.00106097979005, 0.00157986301929, 0.000611628696788, 0.00424165232107, -0.0108361830935, 0.00848229136318, -0.013483710587, 0.0175631288439, -0.0261919125915, 0.0492183603346, -0.0361976921558, 0.0156485214829, -0.00472129974514], [0.00169215211645, 0.00221109832637, 0.0019297208637, -0.00206652842462, 0.00938816089183, -0.00524017866701, 0.0129565084353, -0.0117014469579, 0.0167443696409, -0.0361976921558, 0.0667793750763, -0.0408585630357, 0.0165596082807], [-0.00159456033725, 0.0017813667655, -0.00258888956159, -3.91081921407e-05, 0.00441553862765, -0.00175369891804, -0.000686178333126, 0.00359933800064, -0.0111271934584, 0.0156485214829, -0.0408585630357, 0.0620318576694, -0.0373992063105], [0.00274025090039, -0.00231404229999, 0.00449534785002, 0.00218622013927, -0.00886153429747, 0.000651831331197, -0.00250505725853, -0.00261272280477, 0.00925393775105, -0.00472129974514, 0.0165596082807, -0.0373992063105, 0.0479748286307]]
    },
    "spectral_contrast_coeffs": {
        "dmean": [0.0463346093893, 0.0570665746927, 0.0358777083457, 0.02320625633, 0.0148480180651, 0.0110256960616],
        "dmean2": [0.0700902193785, 0.0872510820627, 0.0573412142694, 0.0357453711331, 0.0231955628842, 0.0166296828538],
        "dvar": [0.00166533165611, 0.00235088914633, 0.000996125745587, 0.000306436792016, 0.000148990307935, 0.000127327046357],
        "dvar2": [0.00297447759658, 0.00380579102784, 0.00221577356569, 0.000800821464509, 0.000305824331008, 0.000264363974566],
        "max": [-0.269241273403, -0.27704885602, -0.676746964455, -0.747979938984, -0.772593140602, -0.798176169395],
        "mean": [-0.516649484634, -0.619008898735, -0.810365915298, -0.850927710533, -0.865914344788, -0.865119040012],
        "median": [-0.489765197039, -0.598151564598, -0.811009407043, -0.85454928875, -0.869244456291, -0.867413520813],
        "min": [-0.848958551884, -0.932745099068, -0.928130567074, -0.918551325798, -0.910421192646, -0.956522643566],
        "var": [0.0183622464538, 0.0189919751137, 0.00353167252615, 0.00107700121589, 0.000574498961214, 0.000294998142635]
    },
    "spectral_contrast_valleys": {
        "dmean": [0.410289943218, 0.36588537693, 0.355222672224, 0.335361868143, 0.254541307688, 0.145990341902],
        "dmean2": [0.687754631042, 0.582611143589, 0.543685495853, 0.500908017159, 0.400786489248, 0.247774168849],
        "dvar": [0.125437214971, 0.0991432517767, 0.113992489874, 0.0985251665115, 0.091557867825, 0.0521720722318],
        "dvar2": [0.351198345423, 0.22783409059, 0.288674771786, 0.21795374155, 0.247341111302, 0.140136986971],
        "max": [-7.04437685013, -6.26889610291, -7.16418886185, -8.24175643921, -8.231133461, -10.6287336349],
        "mean": [-10.0739746094, -8.39252758026, -9.2180480957, -9.67694568634, -9.96853923798, -12.0979013443],
        "median": [-10.1124000549, -8.34055519104, -9.19961929321, -9.60394954681, -9.99113845825, -12.1548461914],
        "min": [-11.2988672256, -10.2709465027, -10.8658752441, -11.1952848434, -11.0668354034, -12.4575490952],
        "var": [0.278349041939, 0.499615550041, 0.6544880867, 0.508953511715, 0.259266644716, 0.0701883733273]
    }
},
"metadata": {
    "audio_properties": {
        "analysis_sample_rate": 44100,
        "bit_rate": 705600,
        "equal_loudness": 0,
        "length": 4.37696123123,
        "lossless": 1,
        "replay_gain": 26.7970867157,
        "sample_rate": 44100,
        "codec": "pcm_s16le",
        "downmix": "mix",
        "md5_encoded": "758a1c03d94dff07de6f3914ac2559f0"
    },
    "tags": {
        "file_name": "000617.wav"
    },
    "version": {
        "essentia": "2.1-beta2",
        "essentia_git_sha": "Undefined",
        "extractor": "music 1.0"
    }
},
"rhythm": {
    "beats_count": 5,
    "beats_loudness": {
        "dmean": 0.0131407277659,
        "dmean2": 0.0327971018851,
        "dvar": 0.000397535128286,
        "dvar2": 0.000419622432673,
        "max": 0.0523113757372,
        "mean": 0.0223364103585,
        "median": 0.00400056317449,
        "min": 0.000571549811866,
        "var": 0.000578706618398
    },
    "bpm": 76.5667037964,
    "bpm_histogram_first_peak_bpm": {
        "dmean": 0,
        "dmean2": 0,
        "dvar": 0,
        "dvar2": 0,
        "max": 76,
        "mean": 76,
        "median": 76,
        "min": 76,
        "var": 0
    },
    "bpm_histogram_first_peak_spread": {
        "dmean": 0,
        "dmean2": 0,
        "dvar": 0,
        "dvar2": 0,
        "max": 0,
        "mean": 0,
        "median": 0,
        "min": 0,
        "var": 0
    },
    "bpm_histogram_first_peak_weight": {
        "dmean": 0,
        "dmean2": 0,
        "dvar": 0,
        "dvar2": 0,
        "max": 1,
        "mean": 1,
        "median": 1,
        "min": 1,
        "var": 0
    },
    "bpm_histogram_second_peak_bpm": {
        "dmean": 0,
        "dmean2": 0,
        "dvar": 0,
        "dvar2": 0,
        "max": 0,
        "mean": 0,
        "median": 0,
        "min": 0,
        "var": 0
    },
    "bpm_histogram_second_peak_spread": {
        "dmean": 0,
        "dmean2": 0,
        "dvar": 0,
        "dvar2": 0,
        "max": 0,
        "mean": 0,
        "median": 0,
        "min": 0,
        "var": 0
    },
    "bpm_histogram_second_peak_weight": {
        "dmean": 0,
        "dmean2": 0,
        "dvar": 0,
        "dvar2": 0,
        "max": 0,
        "mean": 0,
        "median": 0,
        "min": 0,
        "var": 0
    },
    "danceability": 0.904571771622,
    "onset_rate": 2.734375,
    "beats_loudness_band_ratio": {
        "dmean": [0.276956707239, 0.236920565367, 0.0778609886765, 0.00966402608901, 0.00143036257941, 0.00606245081872],
        "dmean2": [0.672180354595, 0.561553418636, 0.138547182083, 0.0149001600221, 0.00220241141506, 0.00950783956796],
        "dvar": [0.0331422835588, 0.0194235593081, 0.00192755251192, 1.45003759826e-05, 1.05691822228e-06, 6.55727199046e-05],
        "dvar2": [0.0319071374834, 0.0209630969912, 0.00312728085555, 3.92637921323e-05, 1.00869658581e-06, 5.87072318012e-05],
        "max": [0.493687689304, 0.926032781601, 0.123343452811, 0.0159420352429, 0.00516091985628, 0.0235549714416],
        "mean": [0.170024514198, 0.769181668758, 0.0541246309876, 0.00911231711507, 0.00265544792637, 0.00641010235995],
        "median": [0.110851034522, 0.789099991322, 0.0162831936032, 0.00745880883187, 0.00230854819529, 0.00370314228348],
        "min": [0.0149444118142, 0.516531407833, 0.0129889464006, 0.000851734366734, 0.000341961334925, 0.000280169741018],
        "var": [0.0287240333855, 0.0188862495124, 0.00242372858338, 3.5625162127e-05, 3.88626131098e-06, 7.61692499509e-05]
    },
    "beats_position": [0.766258478165, 1.54412698746, 2.33360528946, 3.11147379875, 3.90095233917]
},
"tonal": {
    "chords_changes_rate": 0.104166664183,
    "chords_number_rate": 0.0833333358169,
    "chords_strength": {
        "dmean": 0.0130404727533,
        "dmean2": 0.0145079540089,
        "dvar": 9.23958432395e-05,
        "dvar2": 0.000162449461641,
        "max": 0.539349675179,
        "mean": 0.420650482178,
        "median": 0.417225629091,
        "min": 0.258724331856,
        "var": 0.00429024454206
    },
    "hpcp_entropy": {
        "dmean": 0.643153727055,
        "dmean2": 1.04513478279,
        "dvar": 0.213008895516,
        "dvar2": 0.533347785473,
        "max": 4.68705511093,
        "mean": 1.91002333164,
        "median": 1.83100521564,
        "min": 0.0379668585956,
        "var": 0.766863584518
    },
    "key_strength": 0.266385495663,
    "tuning_diatonic_strength": 0.381779938936,
    "tuning_equal_tempered_deviation": 0.260470598936,
    "tuning_frequency": 434.444000244,
    "tuning_nontempered_energy_ratio": 0.900620520115,
    "hpcp": {
        "dmean": [0.0341482236981, 0.0501549653709, 0.0467437803745, 0.0667187571526, 0.104458831251, 0.107592560351, 0.072561442852, 0.0624680630863, 0.0624137111008, 0.0966927558184, 0.115984618664, 0.106452852488, 0.115440957248, 0.145605355501, 0.181240782142, 0.155120551586, 0.16730183363, 0.201412275434, 0.18271163106, 0.222995623946, 0.232268169522, 0.207404688001, 0.223521366715, 0.190796300769, 0.176365062594, 0.154859185219, 0.0870947316289, 0.0583643056452, 0.0298579987139, 0.0423749685287, 0.0545447282493, 0.0481573194265, 0.0301859900355, 0.0327549912035, 0.0326618812978, 0.0265996810049],
        "dmean2": [0.0585109628737, 0.0871497243643, 0.078308686614, 0.120564959943, 0.182257801294, 0.191212445498, 0.121060229838, 0.116865850985, 0.113863527775, 0.171426594257, 0.201799154282, 0.185459911823, 0.199243336916, 0.241386026144, 0.328785151243, 0.288116574287, 0.319013625383, 0.378374248743, 0.327376753092, 0.412499815226, 0.427384912968, 0.343839645386, 0.408880710602, 0.336809098721, 0.302379459143, 0.285511761904, 0.149355083704, 0.103860124946, 0.0527586229146, 0.0704698190093, 0.0941323339939, 0.0831232890487, 0.050371941179, 0.0574992522597, 0.0564716048539, 0.0420303419232],
        "dvar": [0.0072614159435, 0.0228507071733, 0.0191435217857, 0.0332963131368, 0.057659484446, 0.0591424331069, 0.0218202322721, 0.0317244119942, 0.0150899281725, 0.0383784286678, 0.049282155931, 0.0469980351627, 0.0513942576945, 0.069227963686, 0.0909563601017, 0.0813015922904, 0.0813093781471, 0.102992035449, 0.079215593636, 0.096046499908, 0.0800826400518, 0.0748244225979, 0.0800821334124, 0.0670296102762, 0.0762766003609, 0.0575276017189, 0.0268380641937, 0.0210758391768, 0.00552015285939, 0.00934224855155, 0.0139394626021, 0.00972202979028, 0.00465998752043, 0.00577188050374, 0.00732843857259, 0.00354123930447],
        "dvar2": [0.0192742645741, 0.0636006370187, 0.0367703810334, 0.0907519087195, 0.175053596497, 0.153431087732, 0.0568172819912, 0.0982786640525, 0.0461527444422, 0.105882391334, 0.129152148962, 0.133973926306, 0.13048453629, 0.182546213269, 0.280457496643, 0.235989272594, 0.2341427356, 0.307128250599, 0.255320757627, 0.310386419296, 0.216720178723, 0.210282728076, 0.25406447053, 0.179734393954, 0.192469224334, 0.179645881057, 0.0719057768583, 0.0582336932421, 0.0126549005508, 0.0257882606238, 0.0408654473722, 0.0270812213421, 0.00870306883007, 0.0143508147448, 0.0185293927789, 0.00840756297112],
        "max": [0.514155864716, 1, 1, 1, 1, 1, 0.772494316101, 1, 0.658849179745, 1, 1, 1, 1, 1, 1, 1, 1, 1, 1, 1, 1, 1, 1, 1, 1, 1, 1, 0.786260724068, 0.430667102337, 0.518493831158, 0.721924185753, 0.535259187222, 0.314197212458, 0.517117381096, 0.622128784657, 0.396588802338],
        "mean": [0.0261033121496, 0.0373907536268, 0.0389724299312, 0.0486720018089, 0.0827946588397, 0.0964298844337, 0.0719395652413, 0.0529821552336, 0.0586887337267, 0.0858668759465, 0.0939835011959, 0.0798330754042, 0.0984876155853, 0.130783215165, 0.133678525686, 0.119954712689, 0.140144467354, 0.184975370765, 0.181327462196, 0.167238116264, 0.236707314849, 0.275295525789, 0.21632309258, 0.216953620315, 0.233639523387, 0.151261538267, 0.0734187960625, 0.0449853949249, 0.0308185722679, 0.0375034213066, 0.046574562788, 0.0417475253344, 0.0298983026296, 0.0251326486468, 0.0274596232921, 0.0239544082433],
        "median": [0.00115382298827, 0.00163429090753, 0.00241005397402, 0.00206551607698, 0.00215468811803, 0.00238578813151, 0.00268322904594, 0.00347350910306, 0.00475414935499, 0.00702777784318, 0.00522208493203, 0.00544734857976, 0.00215633190237, 0.00147731788456, 0.00143609661609, 0.00182141223922, 0.00342897023074, 0.00396678783, 0.00414560642093, 0.017884509638, 0.0581392757595, 0.0440535098314, 0.0646782889962, 0.0430026240647, 0.034819431603, 0.0205145329237, 0.00613730959594, 0.00120975985192, 0.0013506540563, 0.00311852572486, 0.00191872171126, 0.00108235888183, 0.000929340370931, 0.00105595041532, 0.00146394222975, 0.00192741723731],
        "min": [1.51316535266e-05, 1.95029642782e-05, 5.08853554493e-05, 3.90866625821e-05, 1.70027542481e-05, 3.90050408896e-05, 2.67869527306e-05, 5.23566814081e-05, 1.22809587992e-05, 1.01313953564e-05, 1.59838691616e-05, 1.73050066223e-05, 8.79569233803e-06, 7.88104262028e-06, 8.36083836475e-06, 9.78997559287e-06, 1.15528255265e-05, 1.23969593915e-05, 8.71371594258e-06, 2.50740758929e-05, 5.02111324749e-05, 7.26596044842e-05, 1.40512574944e-05, 7.42650991015e-06, 1.21164184748e-05, 9.90257285594e-06, 1.14889944598e-05, 5.8197783801e-06, 5.43916621609e-06, 8.44074111228e-06, 1.04117107185e-05, 8.67839207785e-06, 2.06066251849e-05, 1.87626701518e-05, 6.6313273237e-06, 1.02556568891e-05],
        "var": [0.00620919791982, 0.0159724559635, 0.0164542682469, 0.0226592943072, 0.0456978268921, 0.0568225197494, 0.0286690760404, 0.0253497455269, 0.0162301901728, 0.0335335321724, 0.0419793985784, 0.0385892763734, 0.0525590926409, 0.0751031413674, 0.0760658159852, 0.0686742067337, 0.0717230662704, 0.108828663826, 0.0977654978633, 0.084775917232, 0.0976961478591, 0.134162530303, 0.0896280631423, 0.100075550377, 0.12754291296, 0.0628050789237, 0.0247608665377, 0.0162859056145, 0.00641109980643, 0.00859589315951, 0.0120231257752, 0.00888562854379, 0.00527222640812, 0.0049073509872, 0.00621437979862, 0.00365771143697]
    },
    "chords_histogram": [0, 38.5416679382, 3.125, 0, 0, 0, 0, 0, 0, 0, 0, 0, 1.04166662693, 0, 8.33333301544, 0, 9.375, 0, 14.5833330154, 0, 0, 14.5833330154, 0, 10.4166669846],
    "thpcp": [1, 0.785785019398, 0.788075387478, 0.848686218262, 0.549451470375, 0.266690850258, 0.16340765357, 0.111947230995, 0.136229678988, 0.169180244207, 0.151646211743, 0.108604386449, 0.0912933424115, 0.0997459813952, 0.0870134308934, 0.094819240272, 0.135820418596, 0.141565799713, 0.176799103618, 0.300748288631, 0.35027769208, 0.261317610741, 0.192455559969, 0.213184475899, 0.311908006668, 0.341391324997, 0.289990454912, 0.357752323151, 0.475064814091, 0.48558190465, 0.435730695724, 0.50906920433, 0.671915650368, 0.658664762974, 0.607485771179, 0.859829843044],
    "chords_key": "C",
    "chords_scale": "major",
    "key_key": "A",
    "key_scale": "minor"
}
}